django_silly_adminplus/__init__.py
django_silly_adminplus/management/__init__.py
django_silly_adminplus/management/commands/__init__.py
django_silly_adminplus/management/commands/get_adminplus+.py
django_silly_adminplus/management/commands/get_adminplus.py
django_silly_adminplus/plop/__init__.py
django_silly_adminplus/plop/adminplus/__init__.py
django_silly_adminplus/plop/adminplus/_adminplus/__init__.py
django_silly_adminplus/plop/adminplus/_adminplus/urls.py
django_silly_adminplus/plop/adminplus/_adminplus/views.py
django_silly_adminplus/plop/adminplus/_adminplus/templates/__init__.py
django_silly_adminplus/plop/adminplus/_adminplus/templates/_adminplus/__init__.py
django_silly_adminplus/plop/adminplus/_adminplus/templates/_adminplus/adminplus.html
django_silly_adminplus/plop/adminplus/_adminplus/templates/admin/__init__.py
django_silly_adminplus/plop/adminplus/_adminplus/templates/admin/base.html
django_silly_adminplus/plop/adminplus_plus/__init__.py
django_silly_adminplus/plop/adminplus_plus/_adminplus/__init__.py
django_silly_adminplus/plop/adminplus_plus/_adminplus/forms.py
django_silly_adminplus/plop/adminplus_plus/_adminplus/models.py
django_silly_adminplus/plop/adminplus_plus/_adminplus/urls.py
django_silly_adminplus/plop/adminplus_plus/_adminplus/views.py
django_silly_adminplus/plop/adminplus_plus/_adminplus/management/__init__.py
django_silly_adminplus/plop/adminplus_plus/_adminplus/management/commands/__init__.py
django_silly_adminplus/plop/adminplus_plus/_adminplus/management/commands/adminplus_init.py
django_silly_adminplus/plop/adminplus_plus/_adminplus/templates/__init__.py
django_silly_adminplus/plop/adminplus_plus/_adminplus/templates/_adminplus/__init__.py
django_silly_adminplus/plop/adminplus_plus/_adminplus/templates/_adminplus/adminplus.html
django_silly_adminplus/plop/adminplus_plus/_adminplus/templates/admin/__init__.py
django_silly_adminplus/plop/adminplus_plus/_adminplus/templates/admin/base.html
django_silly_adminplus-1.0.5.dist-info/LICENSE.md
django_silly_adminplus-1.0.5.dist-info/METADATA
django_silly_adminplus-1.0.5.dist-info/WHEEL
django_silly_adminplus-1.0.5.dist-info/top_level.txt
django_silly_adminplus-1.0.5.dist-info/RECORD
