Metadata-Version: 2.1
Name: django-silly-adminplus
Version: 1.0.5
Summary: Add quickly a new page to your admin site
Home-page: https://github.com/byoso/django-silly-adminplus
Author: Vincent Fabre
Author-email: peigne.plume@gmail.com
License: MIT
Keywords: django adminplus admin
Platform: UNKNOWN
Classifier: License :: OSI Approved :: MIT License
Classifier: Programming Language :: Python :: 3
Classifier: Development Status :: 4 - Beta
Classifier: License :: OSI Approved :: MIT License
Classifier: Natural Language :: English
Requires-Python: >=3.7
License-File: LICENSE.md
